apocryphes/__init__.py
apocryphes/pool.py
apocryphes/rider.py
estoult-0.8.0.dist-info/METADATA
estoult-0.8.0.dist-info/WHEEL
estoult-0.8.0.dist-info/entry_points.txt
estoult-0.8.0.dist-info/licenses/LICENSE
estoult.py
estoult-0.8.0.dist-info/RECORD
