Metadata-Version: 2.1
Name: estoult
Version: 0.8.0
Summary: Data mapper and query builder for SQL databases.
Author-Email: Justin Duch <justin@duch.me>
License: MIT
Classifier: Development Status :: 5 - Production/Stable
Classifier: Intended Audience :: Developers
Classifier: License :: OSI Approved :: MIT License
Classifier: Operating System :: OS Independent
Classifier: Programming Language :: Python :: 3.9
Classifier: Programming Language :: Python :: 3.10
Classifier: Programming Language :: Python :: 3.11
Classifier: Programming Language :: Python :: 3.12
Classifier: Programming Language :: Python :: 3.13
Classifier: Topic :: Software Development :: Libraries :: Python Modules
Project-URL: Homepage, https://github.com/halcyonnouveau/estoult
Requires-Python: >=3.9
Provides-Extra: mysql
Requires-Dist: mysqlclient>=2.0.0; extra == "mysql"
Provides-Extra: postgres
Requires-Dist: psycopg2-binary>=2.9.0; extra == "postgres"
